setup.py
django_tip.egg-info/PKG-INFO
django_tip.egg-info/SOURCES.txt
django_tip.egg-info/dependency_links.txt
django_tip.egg-info/top_level.txt
tip/__init__.py
tip/actions.py
tip/filesystem.py
tip/filters.py
tip/management/__init__.py
tip/management/commands/__init__.py
tip/management/commands/tip.py
tip/tests/__init__.py
tip/tests/helpers.py
tip/tests/functional/__init__.py
tip/tests/functional/test_basic_infra.py
tip/tests/functional/test_filesystem_locator.py
tip/tests/functional/test_help_command.py
tip/tests/functional/test_template_inclusion.py
tip/tests/functional/test_template_inclusion_command.py
tip/tests/functional/test_template_listing.py
tip/tests/functional/test_template_listing_command.py
tip/tests/functional/test_template_path_listing.py
tip/tests/functional/test_template_path_listing_command.py
tip/tests/functional/test_template_validation.py