Metadata-Version: 1.0
Name: django-tip
Version: 0.3
Summary: Inspector for Django Templates
Home-page: http://github.com/ricobl/django-template-inspector
Author: Enrico Batista
Author-email: ricobl@gmail.com
License: UNKNOWN
Platform: UNKNOWN
